bareasgi_rest/__init__.py
bareasgi_rest/arg_builder.py
bareasgi_rest/constants.py
bareasgi_rest/helpers.py
bareasgi_rest/py.typed
bareasgi_rest/rest_router.py
bareasgi_rest/serialization/__init__.py
bareasgi_rest/serialization/json.py
bareasgi_rest/serialization/xml.py
bareasgi_rest/swagger/__init__.py
bareasgi_rest/swagger/config.py
bareasgi_rest/swagger/controller.py
bareasgi_rest/swagger/entry.py
bareasgi_rest/swagger/errors.py
bareasgi_rest/swagger/parameters.py
bareasgi_rest/swagger/paths.py
bareasgi_rest/swagger/properties.py
bareasgi_rest/swagger/repository.py
bareasgi_rest/swagger/responses.py
bareasgi_rest/swagger/utils.py
bareasgi_rest/templates/swagger.html
bareasgi_rest/types.py
bareasgi_rest/utils.py
bareasgi_rest-4.0.1.dist-info/WHEEL
bareasgi_rest-4.0.1.dist-info/METADATA
bareasgi_rest-4.0.1.dist-info/RECORD
