Metadata-Version: 2.1
Name: bareasgi-rest
Version: 4.0.1
Summary: REST support for bareASGI
Home-page: https://github.com/rob-blackbourn/bareASGI-rest
License: Apache-2.0
Keywords: bareASGI,rest,swagger
Author: Rob Blackbourn
Author-email: rob.blackbourn@gmail.com
Requires-Python: >=3.8,<4.0
Classifier: License :: OSI Approved :: Apache Software License
Classifier: Programming Language :: Python :: 3
Classifier: Programming Language :: Python :: 3.10
Classifier: Programming Language :: Python :: 3.8
Classifier: Programming Language :: Python :: 3.9
Requires-Dist: bareasgi (>=4.2,<5.0)
Requires-Dist: bareasgi-jinja2 (>=4.0,<5.0)
Requires-Dist: docstring-parser (>=0.15,<0.16)
Requires-Dist: jetblack-serialization (>=3.0.1,<4.0.0)
Requires-Dist: lxml (>=4.9,<5.0)
Requires-Dist: stringcase (>=1.2,<2.0)
Requires-Dist: typing-extensions (>=4,<5)
Requires-Dist: typing_inspect (>=0.8,<0.9)
Project-URL: Repository, https://github.com/rob-blackbourn/bareASGI-rest
